marshmallow_dataframe/__init__.py
marshmallow_dataframe/base.py
marshmallow_dataframe/converters.py
marshmallow_dataframe/records.py
marshmallow_dataframe/split.py
marshmallow_dataframe-0.1.4.dist-info/LICENSE
marshmallow_dataframe-0.1.4.dist-info/METADATA
marshmallow_dataframe-0.1.4.dist-info/WHEEL
marshmallow_dataframe-0.1.4.dist-info/top_level.txt
marshmallow_dataframe-0.1.4.dist-info/RECORD
