Metadata-Version: 2.1
Name: marshmallow-dataframe
Version: 0.1.4
Summary: Marshmallow Schema generator for pandas dataframes
Home-page: https://github.com/facultyai/marshmallow-dataframe
Author: Faculty
Author-email: opensource@faculty.ai
License: Apache Software License
Platform: UNKNOWN
Requires-Python: >=3.6
Requires-Dist: marshmallow (>=3.0.1)
Requires-Dist: pandas
Requires-Dist: numpy
